quicksqlconnector/__init__.py
quicksqlconnector/tempCodeRunnerFile.py
quicksqlconnector/test.py
quicksqlconnector-1.5.3.dist-info/LICENSE
quicksqlconnector-1.5.3.dist-info/METADATA
quicksqlconnector-1.5.3.dist-info/WHEEL
quicksqlconnector-1.5.3.dist-info/top_level.txt
quicksqlconnector-1.5.3.dist-info/RECORD
