Metadata-Version: 2.1
Name: quicksqlconnector
Version: 1.5.3
Summary: Run MySQL, PostgresSQL, SQLite queries with just one line in python. The Ultimate SQL Library.
Home-page: https://quicksqlconnector.web.app/
Author: Anas Raza
Author-email: anasraza1@yahoo.com
License: MIT
Keywords: quicksqlconnector,sql,database,mysql,postgres,sqlite3
Platform: UNKNOWN
Requires-Dist: mysql-connector-python
Requires-Dist: psycopg2
